cool_maps/__init__.py
cool_maps/_version.py
cool_maps/plot.py
cool_maps-0.0.3.dist-info/LICENSE
cool_maps-0.0.3.dist-info/METADATA
cool_maps-0.0.3.dist-info/WHEEL
cool_maps-0.0.3.dist-info/top_level.txt
cool_maps-0.0.3.dist-info/RECORD
