Metadata-Version: 2.1
Name: cool-maps
Version: 0.0.3
Summary: Helper functions around cartopy for plotting data on maps. These functions are written to easily generate nice-looking maps.
Home-page: https://github.com/rucool/cool_maps
Author: Michael Smith
Author-email: michaesm@marine.rutgers.edu
License: MIT
Keywords: cool_maps
Classifier: Development Status :: 2 - Pre-Alpha
Classifier: Intended Audience :: Developers
Classifier: License :: OSI Approved :: MIT License
Classifier: Natural Language :: English
Classifier: Programming Language :: Python :: 3.7
Classifier: Programming Language :: Python :: 3.8
Classifier: Programming Language :: Python :: 3.9
Classifier: Programming Language :: Python :: 3.10
Requires-Python: >=3.7
License-File: LICENSE
Requires-Dist: cartopy (<0.20)
Requires-Dist: matplotlib
Requires-Dist: cmocean
Requires-Dist: oceans
Requires-Dist: numpy
